tno/quantum/communication/qkd_key_rate/__init__.py
tno/quantum/communication/qkd_key_rate/py.typed
tno/quantum/communication/qkd_key_rate/_utils/__init__.py
tno/quantum/communication/qkd_key_rate/_utils/entropy.py
tno/quantum/communication/qkd_key_rate/classical/__init__.py
tno/quantum/communication/qkd_key_rate/classical/_corrector.py
tno/quantum/communication/qkd_key_rate/classical/_message.py
tno/quantum/communication/qkd_key_rate/classical/_parity_strategy.py
tno/quantum/communication/qkd_key_rate/classical/_permutations.py
tno/quantum/communication/qkd_key_rate/classical/_receiver.py
tno/quantum/communication/qkd_key_rate/classical/_required_linktime.py
tno/quantum/communication/qkd_key_rate/classical/_schedule.py
tno/quantum/communication/qkd_key_rate/classical/_sender.py
tno/quantum/communication/qkd_key_rate/classical/cascade.py
tno/quantum/communication/qkd_key_rate/classical/privacy_amplification.py
tno/quantum/communication/qkd_key_rate/classical/winnow.py
tno/quantum/communication/qkd_key_rate/quantum/__init__.py
tno/quantum/communication/qkd_key_rate/quantum/_config.py
tno/quantum/communication/qkd_key_rate/quantum/_detector.py
tno/quantum/communication/qkd_key_rate/quantum/_keyrate.py
tno/quantum/communication/qkd_key_rate/quantum/bb84.py
tno/quantum/communication/qkd_key_rate/quantum/bb84_single_photon.py
tno/quantum/communication/qkd_key_rate/quantum/bbm92.py
tno/quantum/communication/qkd_key_rate/test/base/detectors.csv
tno/quantum/communication/qkd_key_rate/test/base/test_corrector.py
tno/quantum/communication/qkd_key_rate/test/base/test_detector.py
tno/quantum/communication/qkd_key_rate/test/base/test_message.py
tno/quantum/communication/qkd_key_rate/test/base/test_parity_strategy.py
tno/quantum/communication/qkd_key_rate/test/base/test_permutations.py
tno/quantum/communication/qkd_key_rate/test/base/test_schedule.py
tno/quantum/communication/qkd_key_rate/test/classical/test_cascade.py
tno_quantum_communication_qkd_key_rate-2.0.3.dist-info/licenses/LICENSE
tno_quantum_communication_qkd_key_rate-2.0.3.dist-info/METADATA
tno_quantum_communication_qkd_key_rate-2.0.3.dist-info/WHEEL
tno_quantum_communication_qkd_key_rate-2.0.3.dist-info/top_level.txt
tno_quantum_communication_qkd_key_rate-2.0.3.dist-info/RECORD
