Metadata-Version: 2.4
Name: tno.quantum.communication.qkd_key_rate
Version: 2.0.3
Summary: Quantum communication key-rate modules
Author-email: TNO Quantum Code Lab <tnoquantum@tno.nl>
Maintainer-email: TNO Quantum Code Lab <tnoquantum@tno.nl>
License: Apache License, Version 2.0
Project-URL: Homepage, https://github.com/TNO-Quantum/
Project-URL: Documentation, https://github.com/TNO-Quantum/
Project-URL: Source, https://ci.tno.nl/gitlab/quantum/quantum-key-distribution/key-rate-modules
Keywords: TNO,Quantum,Quantum Key Distribution
Platform: any
Classifier: License :: OSI Approved :: Apache Software License
Classifier: Programming Language :: Python :: 3
Classifier: Programming Language :: Python :: 3.9
Classifier: Programming Language :: Python :: 3.10
Classifier: Programming Language :: Python :: 3.11
Classifier: Programming Language :: Python :: 3.12
Classifier: Programming Language :: Python :: 3.13
Classifier: Operating System :: OS Independent
Classifier: Intended Audience :: Developers
Classifier: Intended Audience :: Information Technology
Classifier: Intended Audience :: Science/Research
Classifier: Typing :: Typed
Requires-Python: >=3.9
License-File: LICENSE
Requires-Dist: numpy
Requires-Dist: scipy
Requires-Dist: pandas
Requires-Dist: matplotlib
Requires-Dist: tno.quantum.utils~=5.1
Provides-Extra: tests
Requires-Dist: pytest>=8.1.1; extra == "tests"
Requires-Dist: pytest-cov>=4.1.0; extra == "tests"
Requires-Dist: tomlkit; extra == "tests"
Dynamic: license-file
